examples/__init__.py
examples/desktop_authenticator.py
examples/inventory.py
examples/storehouse.py
steampy/__init__.py
steampy/client.py
steampy/confirmation.py
steampy/exceptions.py
steampy/guard.py
steampy/login.py
steampy/market.py
steampy/models.py
steampy/utils.py
test/__init__.py
test/test_client.py
test/test_guard.py
test/test_market.py
test/test_utils.py
projectjoki_steampy-1.1.2.dist-info/LICENSE.txt
projectjoki_steampy-1.1.2.dist-info/METADATA
projectjoki_steampy-1.1.2.dist-info/WHEEL
projectjoki_steampy-1.1.2.dist-info/top_level.txt
projectjoki_steampy-1.1.2.dist-info/RECORD
