Metadata-Version: 2.1
Name: projectjoki-steampy
Version: 1.1.2
Summary: A Steam lib for trade automation
Home-page: https://github.com/bukson/steampy
Download-URL: https://github.com/bukson/steampy/tarball/1.1.2
Author: Michał Bukowski
Author-email: gigibukson@gmail.com
License: MIT
Keywords: steam,trade
License-File: LICENSE.txt
Requires-Dist: requests
Requires-Dist: beautifulsoup4
Requires-Dist: rsa
